README.rst
setup.py
china_stock.egg-info/PKG-INFO
china_stock.egg-info/SOURCES.txt
china_stock.egg-info/dependency_links.txt
china_stock.egg-info/entry_points.txt
china_stock.egg-info/top_level.txt
chinastock/__init__.py
chinastock/source/__init__.py
chinastock/source/netease.py
chinastock/stock/__init__.py
chinastock/stock/basic.py
chinastock/stock/service.py
test/__init__.py
test/stock_test.py